{
  "title": "Screenshot_20221028-233409.png",
  "description": "",
  "imageViews": "12",
  "creationTime": {
    "timestamp": "1667024764",
    "formatted": "Oct 29, 2022, 6:26:04 AM UTC"
  },
  "photoTakenTime": {
    "timestamp": "1667021649",
    "formatted": "Oct 29, 2022, 5:34:09 AM UTC"
  },
  "geoData": {
    "latitude": 0.0,
    "longitude": 0.0,
    "altitude": 0.0,
    "latitudeSpan": 0.0,
    "longitudeSpan": 0.0
  },
  "geoDataExif": {
    "latitude": 0.0,
    "longitude": 0.0,
    "altitude": 0.0,
    "latitudeSpan": 0.0,
    "longitudeSpan": 0.0
  },
  "url": "https://photos.google.com/photo/AF1QipP2WZC2JzoY55qkMrv2dxjie4A5fd38kW2Zv_C5",
  "googlePhotosOrigin": {
    "mobileUpload": {
      "deviceFolder": {
        "localFolderName": ""
      },
      "deviceType": "ANDROID_PHONE"
    }
  }
}