{
  "title": "IMG_20221004_174353505.jpg",
  "description": "",
  "imageViews": "9",
  "creationTime": {
    "timestamp": "1667010009",
    "formatted": "Oct 29, 2022, 2:20:09 AM UTC"
  },
  "photoTakenTime": {
    "timestamp": "1664927034",
    "formatted": "Oct 4, 2022, 11:43:54 PM UTC"
  },
  "geoData": {
    "latitude": 35.150717,
    "longitude": -106.49907599999999,
    "altitude": 1809.5,
    "latitudeSpan": 0.0,
    "longitudeSpan": 0.0
  },
  "geoDataExif": {
    "latitude": 35.150717,
    "longitude": -106.49907599999999,
    "altitude": 1809.5,
    "latitudeSpan": 0.0,
    "longitudeSpan": 0.0
  },
  "url": "https://photos.google.com/photo/AF1QipOCdHUmWRZG-Sv02C2_dK9vDSOEu-3eB00vVtJS",
  "googlePhotosOrigin": {
    "mobileUpload": {
      "deviceFolder": {
        "localFolderName": ""
      },
      "deviceType": "ANDROID_PHONE"
    }
  }
}