{
  "title": "Screenshot_20220831-220143.png",
  "description": "",
  "imageViews": "8",
  "creationTime": {
    "timestamp": "1666996938",
    "formatted": "Oct 28, 2022, 10:42:18 PM UTC"
  },
  "photoTakenTime": {
    "timestamp": "1662004903",
    "formatted": "Sep 1, 2022, 4:01:43 AM UTC"
  },
  "geoData": {
    "latitude": 0.0,
    "longitude": 0.0,
    "altitude": 0.0,
    "latitudeSpan": 0.0,
    "longitudeSpan": 0.0
  },
  "geoDataExif": {
    "latitude": 0.0,
    "longitude": 0.0,
    "altitude": 0.0,
    "latitudeSpan": 0.0,
    "longitudeSpan": 0.0
  },
  "url": "https://photos.google.com/photo/AF1QipOlinpKTTMs7NckddZjloLJ9wyOXE5UXZgKSdNz",
  "googlePhotosOrigin": {
    "mobileUpload": {
      "deviceFolder": {
        "localFolderName": ""
      },
      "deviceType": "ANDROID_PHONE"
    }
  }
}